napari_roi_manager/__init__.py
napari_roi_manager/_dataclasses.py
napari_roi_manager/napari.yaml
napari_roi_manager/_tests/__init__.py
napari_roi_manager/_tests/_test_roiset.json
napari_roi_manager/_tests/test-rois.zip
napari_roi_manager/_tests/test_widget.py
napari_roi_manager/ij/__init__.py
napari_roi_manager/ij/_convert.py
napari_roi_manager/layers/__init__.py
napari_roi_manager/layers/_key_bindings.py
napari_roi_manager/layers/_layer.py
napari_roi_manager/widgets/__init__.py
napari_roi_manager/widgets/_dialogs.py
napari_roi_manager/widgets/_roi_manager.py
napari_roi_manager-0.0.6.dist-info/METADATA
napari_roi_manager-0.0.6.dist-info/WHEEL
napari_roi_manager-0.0.6.dist-info/entry_points.txt
napari_roi_manager-0.0.6.dist-info/licenses/LICENSE
napari_roi_manager-0.0.6.dist-info/RECORD
