Metadata-Version: 2.4
Name: napari-roi-manager
Version: 0.0.6
Summary: A ROI Manager Widget with an UI similar to ImageJ
Project-URL: Bug Tracker, https://github.com/hanjinliu/napari-roi-manager/issues
Project-URL: Documentation, https://github.com/hanjinliu/napari-roi-manager#README.md
Project-URL: Homepage, https://github.com/hanjinliu/napari-roi-manager
Project-URL: Source Code, https://github.com/hanjinliu/napari-roi-manager
Project-URL: User Support, https://github.com/hanjinliu/napari-roi-manager/issues
Author-email: Hanjin Liu <liuhanjin.sc@gmail.com>
License-Expression: BSD-3-Clause
License-File: LICENSE
Classifier: Development Status :: 2 - Pre-Alpha
Classifier: Framework :: napari
Classifier: Intended Audience :: Developers
Classifier: License :: OSI Approved :: BSD License
Classifier: Operating System :: OS Independent
Classifier: Programming Language :: Python
Classifier: Programming Language :: Python :: 3
Classifier: Programming Language :: Python :: 3 :: Only
Classifier: Programming Language :: Python :: 3.10
Classifier: Programming Language :: Python :: 3.11
Classifier: Programming Language :: Python :: 3.12
Classifier: Programming Language :: Python :: 3.13
Classifier: Topic :: Scientific/Engineering :: Image Processing
Requires-Python: >=3.10
Requires-Dist: numpy
Requires-Dist: qtpy
Requires-Dist: roifile
Provides-Extra: testing
Requires-Dist: napari; extra == 'testing'
Requires-Dist: pyqt5; extra == 'testing'
Requires-Dist: pytest; extra == 'testing'
Requires-Dist: pytest-cov; extra == 'testing'
Requires-Dist: pytest-qt; extra == 'testing'
Requires-Dist: tox; extra == 'testing'
